zhengyang_env_3/__init__.py
zhengyang_env_3/envs/__init__.py
zhengyang_env_3/envs/kuka.py
zhengyang_env_3/envs/zhengyang_env_3.py
zhengyang_env_3-0.0.2.dist-info/METADATA
zhengyang_env_3-0.0.2.dist-info/WHEEL
zhengyang_env_3-0.0.2.dist-info/top_level.txt
zhengyang_env_3-0.0.2.dist-info/RECORD
